{
  "generated_at": "2026-07-19T15:38:47.211327+00:00",
  "duration_seconds": 315.3,
  "n_candidates_discovered": 1284,
  "n_candidates_evaluated": 60,
  "n_passed_filters": 10,
  "n_errors": 1,
  "errors": [
    {
      "wallet": "0x076daa87c4fe1a85402a9b6b8e0a866224388d4c",
      "error": "GET https://data-api.polymarket.com/trades failed after 3 attempts: 400 Client Error: Bad Request for url: https://data-api.polymarket.com/trades?limit=1000&offset=11000&user=0x076daa87c4fe1a85402a9b6b8e0a866224388d4c"
    }
  ],
  "wallets": [
    {
      "wallet": "0x5966db1fe50763c9e3c014d756369bad07e1f804",
      "userName": "0x5966Db1fE50763C9e3C014d756369BAd07E1F804-1777648534241",
      "display_name": "0x5966Db1fE50763C9e3C014d756369BAd07E1F804-1777648534241",
      "profile_url": "https://polymarket.com/@0x5966Db1fE50763C9e3C014d756369BAd07E1F804-1777648534241",
      "score": {
        "composite": 0.6517,
        "score_100": 83,
        "kelly_edge": 0.6553,
        "weights_used": {
          "clv": 0.25,
          "sharpe": 0.2,
          "roi_lifetime": 0.15,
          "roi_90d": 0.15,
          "drawdown": 0.1,
          "sample_size": 0.1,
          "win_rate": 0.05
        },
        "consistency_adjustment": 0.02,
        "clv": 0.1186,
        "n_clv_with_data": 14,
        "n_clv_attempted": 40,
        "sharpe": 1.2227,
        "roi_lifetime": 0.4293,
        "roi_180d": 0.4293,
        "roi_90d": 0.4293,
        "roi_30d": 0.4266,
        "max_drawdown_fraction": 0.0007,
        "n_resolved": 122,
        "n_distinct_markets": 122,
        "capital_concentration_hhi": 0.021,
        "win_rate_adj": 0.8359,
        "avg_trades_per_day_30d": 1.77
      },
      "radar": {
        "account_age_days": 79.0,
        "portfolio_value": 0,
        "capital_efficiency": 0.2801,
        "best_leaderboard_rank": 37,
        "profile_views": null,
        "reasons": [
          "passes: efficient/small portfolio, low view count, not top-ranked publicly"
        ]
      },
      "open_positions_count": 67,
      "entry_recommendations": []
    },
    {
      "wallet": "0x59f4a4b19fcaa99a4df2e7cdda4919aa5afbc1f1",
      "userName": "BaccaratRoulette",
      "display_name": "BaccaratRoulette",
      "profile_url": "https://polymarket.com/@BaccaratRoulette",
      "score": {
        "composite": 0.6328,
        "score_100": 82,
        "kelly_edge": 0.1664,
        "weights_used": {
          "clv": 0.25,
          "sharpe": 0.2,
          "roi_lifetime": 0.15,
          "roi_90d": 0.15,
          "drawdown": 0.1,
          "sample_size": 0.1,
          "win_rate": 0.05
        },
        "consistency_adjustment": 0.02,
        "clv": 0.173,
        "n_clv_with_data": 38,
        "n_clv_attempted": 40,
        "sharpe": 1.1011,
        "roi_lifetime": 0.2528,
        "roi_180d": 0.334,
        "roi_90d": 0.5799,
        "roi_30d": 0.6204,
        "max_drawdown_fraction": 0.0558,
        "n_resolved": 462,
        "n_distinct_markets": 461,
        "capital_concentration_hhi": 0.0056,
        "win_rate_adj": 0.4847,
        "avg_trades_per_day_30d": 4.07
      },
      "radar": {
        "account_age_days": 458.7,
        "portfolio_value": 11730.28,
        "capital_efficiency": 0.1652,
        "best_leaderboard_rank": 40,
        "profile_views": null,
        "reasons": [
          "passes: efficient/small portfolio, low view count, not top-ranked publicly"
        ]
      },
      "open_positions_count": 146,
      "entry_recommendations": [
        {
          "market_title": "Will Spain win the 2026 FIFA World Cup?",
          "outcome": "Yes",
          "their_entry_price": 0.4664,
          "current_price": 0.5915,
          "fair_value_estimate": 0.5915,
          "suggested_entry_range": [
            0.466,
            0.592
          ],
          "flagged_chasing": true,
          "note": "Price has moved up 0.13 (27%) since their entry of 0.47 -- buying now means chasing, not replicating their original risk/reward.",
          "conviction": 0.0387,
          "pick_score": 0.0077,
          "recommended": true,
          "their_position_value": 11730.276
        }
      ]
    },
    {
      "wallet": "0x69c5c6f6a4dda665991c203bc8d5df3e006b1e01",
      "userName": "Themsnw",
      "display_name": "Themsnw",
      "profile_url": "https://polymarket.com/@Themsnw",
      "score": {
        "composite": 0.5465,
        "score_100": 78,
        "kelly_edge": 0.4994,
        "weights_used": {
          "clv": 0.25,
          "sharpe": 0.2,
          "roi_lifetime": 0.15,
          "roi_90d": 0.15,
          "drawdown": 0.1,
          "sample_size": 0.1,
          "win_rate": 0.05
        },
        "consistency_adjustment": 0.02,
        "clv": 0.0892,
        "n_clv_with_data": 39,
        "n_clv_attempted": 40,
        "sharpe": 1.1874,
        "roi_lifetime": 0.322,
        "roi_180d": 0.322,
        "roi_90d": 0.322,
        "roi_30d": 0.322,
        "max_drawdown_fraction": 0.0288,
        "n_resolved": 47,
        "n_distinct_markets": 46,
        "capital_concentration_hhi": 0.063,
        "win_rate_adj": 0.7231,
        "avg_trades_per_day_30d": 10.53
      },
      "radar": {
        "account_age_days": 17.5,
        "portfolio_value": 137783.78,
        "capital_efficiency": 0.1699,
        "best_leaderboard_rank": 42,
        "profile_views": null,
        "reasons": [
          "passes: efficient/small portfolio, low view count, not top-ranked publicly"
        ]
      },
      "open_positions_count": 39,
      "entry_recommendations": [
        {
          "market_title": "Will LeBron James play for the Miami Heat in 2026-27?",
          "outcome": "Yes",
          "their_entry_price": 0.4064,
          "current_price": 0.4225,
          "fair_value_estimate": 0.4125,
          "suggested_entry_range": [
            0.399,
            0.419
          ],
          "flagged_chasing": false,
          "note": "Price is close to their entry (0.41 -> 0.42); replicating their entry is still reasonably representative.",
          "conviction": 0.0667,
          "pick_score": 0.0667,
          "recommended": true,
          "their_position_value": 102087.9931
        },
        {
          "market_title": "Will LeBron James play for the Golden State Warriors in 2026-27?",
          "outcome": "No",
          "their_entry_price": 0.8969,
          "current_price": 0.8605,
          "fair_value_estimate": 0.864,
          "suggested_entry_range": [
            0.862,
            0.899
          ],
          "flagged_chasing": false,
          "note": "Price is close to their entry (0.90 -> 0.86); replicating their entry is still reasonably representative.",
          "conviction": 0.0094,
          "pick_score": 0.0094,
          "recommended": true,
          "their_position_value": 14390.7606
        },
        {
          "market_title": "Will LeBron James play for the Philadelphia 76ers in 2026-27?",
          "outcome": "Yes",
          "their_entry_price": 0.1591,
          "current_price": 0.0875,
          "fair_value_estimate": 0.0875,
          "suggested_entry_range": [
            0.087,
            0.159
          ],
          "flagged_chasing": false,
          "note": "Price is close to their entry (0.16 -> 0.09); replicating their entry is still reasonably representative.",
          "conviction": 0.0038,
          "pick_score": 0.0038,
          "recommended": true,
          "their_position_value": 5753.7858
        },
        {
          "market_title": "Will Samuel Alito announce his retirement by September 30, 2026?",
          "outcome": "Yes",
          "their_entry_price": 0.1778,
          "current_price": 0.05,
          "fair_value_estimate": 0.05,
          "suggested_entry_range": [
            0.05,
            0.178
          ],
          "flagged_chasing": true,
          "note": "Price has moved down 0.13 (72%) since their entry of 0.18 -- buying now means chasing, not replicating their original risk/reward.",
          "conviction": 0.0079,
          "pick_score": 0.0016,
          "recommended": false,
          "their_position_value": 12108.7283
        },
        {
          "market_title": "Will Samuel Alito announce his retirement by December 31, 2026?",
          "outcome": "Yes",
          "their_entry_price": 0.3144,
          "current_price": 0.105,
          "fair_value_estimate": 0.105,
          "suggested_entry_range": [
            0.105,
            0.314
          ],
          "flagged_chasing": true,
          "note": "Price has moved down 0.21 (67%) since their entry of 0.31 -- buying now means chasing, not replicating their original risk/reward.",
          "conviction": 0.002,
          "pick_score": 0.0004,
          "recommended": false,
          "their_position_value": 3135.1266
        },
        {
          "market_title": "Will LeBron James play for the New York Knicks in 2026-27?",
          "outcome": "Yes",
          "their_entry_price": 0.0395,
          "current_price": 0.0105,
          "fair_value_estimate": 0.0105,
          "suggested_entry_range": [
            0.011,
            0.04
          ],
          "flagged_chasing": false,
          "note": "Price is close to their entry (0.04 -> 0.01); replicating their entry is still reasonably representative.",
          "conviction": 0.0001,
          "pick_score": 0.0001,
          "recommended": false,
          "their_position_value": 165.8928
        },
        {
          "market_title": "Will LeBron James play for the Minnesota Timberwolves in 2026-27?",
          "outcome": "Yes",
          "their_entry_price": 0.0349,
          "current_price": 0.023,
          "fair_value_estimate": 0.019,
          "suggested_entry_range": [
            0.017,
            0.037
          ],
          "flagged_chasing": false,
          "note": "Price is close to their entry (0.03 -> 0.02); replicating their entry is still reasonably representative.",
          "conviction": 0.0001,
          "pick_score": 0.0001,
          "recommended": false,
          "their_position_value": 141.4925
        }
      ]
    },
    {
      "wallet": "0xc41d736bded9ed1accd6a44235039266219774fd",
      "userName": "0xC41D736bDed9ED1acCD6A44235039266219774fD-1777101352681",
      "display_name": "0xC41D736bDed9ED1acCD6A44235039266219774fD-1777101352681",
      "profile_url": "https://polymarket.com/@0xC41D736bDed9ED1acCD6A44235039266219774fD-1777101352681",
      "score": {
        "composite": 0.5044,
        "score_100": 75,
        "kelly_edge": 0.5097,
        "weights_used": {
          "clv": 0.25,
          "sharpe": 0.2,
          "roi_lifetime": 0.15,
          "roi_90d": 0.15,
          "drawdown": 0.1,
          "sample_size": 0.1,
          "win_rate": 0.05
        },
        "consistency_adjustment": 0.02,
        "clv": -0.0171,
        "n_clv_with_data": 38,
        "n_clv_attempted": 40,
        "sharpe": 0.9511,
        "roi_lifetime": 0.4888,
        "roi_180d": 0.4888,
        "roi_90d": 0.4888,
        "roi_30d": 0.5114,
        "max_drawdown_fraction": 0.0147,
        "n_resolved": 121,
        "n_distinct_markets": 120,
        "capital_concentration_hhi": 0.0297,
        "win_rate_adj": 0.7218,
        "avg_trades_per_day_30d": 5.87
      },
      "radar": {
        "account_age_days": 85.3,
        "portfolio_value": 0,
        "capital_efficiency": 0.2293,
        "best_leaderboard_rank": 27,
        "profile_views": null,
        "reasons": [
          "passes: efficient/small portfolio, low view count, not top-ranked publicly"
        ]
      },
      "open_positions_count": 129,
      "entry_recommendations": []
    },
    {
      "wallet": "0xc6a63ad5a788a576d4acc9911c50fef9fde49458",
      "userName": "filthybetz",
      "display_name": "filthybetz",
      "profile_url": "https://polymarket.com/@filthybetz",
      "score": {
        "composite": 0.4802,
        "score_100": 74,
        "kelly_edge": 0.5054,
        "weights_used": {
          "clv": 0.25,
          "sharpe": 0.2,
          "roi_lifetime": 0.15,
          "roi_90d": 0.15,
          "drawdown": 0.1,
          "sample_size": 0.1,
          "win_rate": 0.05
        },
        "consistency_adjustment": 0.02,
        "clv": 0.0187,
        "n_clv_with_data": 24,
        "n_clv_attempted": 29,
        "sharpe": 1.274,
        "roi_lifetime": 0.4391,
        "roi_180d": 0.4391,
        "roi_90d": 0.4391,
        "roi_30d": 0.434,
        "max_drawdown_fraction": 0.0274,
        "n_resolved": 29,
        "n_distinct_markets": 26,
        "capital_concentration_hhi": 0.0636,
        "win_rate_adj": 0.7361,
        "avg_trades_per_day_30d": 2.9
      },
      "radar": {
        "account_age_days": 41.8,
        "portfolio_value": 0,
        "capital_efficiency": 0.2632,
        "best_leaderboard_rank": 24,
        "profile_views": null,
        "reasons": [
          "passes: efficient/small portfolio, low view count, not top-ranked publicly"
        ]
      },
      "open_positions_count": 22,
      "entry_recommendations": []
    },
    {
      "wallet": "0x9ee8bbc36d378af72e5f6b8e2ea2eb67c05a89de",
      "userName": "Qpkwks",
      "display_name": "Qpkwks",
      "profile_url": "https://polymarket.com/@Qpkwks",
      "score": {
        "composite": 0.4454,
        "score_100": 73,
        "kelly_edge": 0.3071,
        "weights_used": {
          "clv": 0.25,
          "sharpe": 0.2,
          "roi_lifetime": 0.15,
          "roi_90d": 0.15,
          "drawdown": 0.1,
          "sample_size": 0.1,
          "win_rate": 0.05
        },
        "consistency_adjustment": 0.02,
        "clv": 0.0501,
        "n_clv_with_data": 33,
        "n_clv_attempted": 33,
        "sharpe": 0.6388,
        "roi_lifetime": 0.4325,
        "roi_180d": 0.4325,
        "roi_90d": 0.4325,
        "roi_30d": 0.4325,
        "max_drawdown_fraction": 0.031,
        "n_resolved": 33,
        "n_distinct_markets": 30,
        "capital_concentration_hhi": 0.068,
        "win_rate_adj": 0.5898,
        "avg_trades_per_day_30d": 10.73
      },
      "radar": {
        "account_age_days": 28.9,
        "portfolio_value": 0,
        "capital_efficiency": 0.2143,
        "best_leaderboard_rank": 28,
        "profile_views": null,
        "reasons": [
          "passes: efficient/small portfolio, low view count, not top-ranked publicly"
        ]
      },
      "open_positions_count": 29,
      "entry_recommendations": []
    },
    {
      "wallet": "0x7583d5f8a1031ff4afcdc6db4e2143bfd41b4df2",
      "userName": "0x7583d5f8A1031fF4AfCDc6db4e2143bFd41b4dF2-1783673385090",
      "display_name": "0x7583d5f8A1031fF4AfCDc6db4e2143bFd41b4dF2-1783673385090",
      "profile_url": "https://polymarket.com/@0x7583d5f8A1031fF4AfCDc6db4e2143bFd41b4dF2-1783673385090",
      "score": {
        "composite": 0.3018,
        "score_100": 65,
        "kelly_edge": 0.1146,
        "weights_used": {
          "clv": 0.25,
          "sharpe": 0.2,
          "roi_lifetime": 0.15,
          "roi_90d": 0.15,
          "drawdown": 0.1,
          "sample_size": 0.1,
          "win_rate": 0.05
        },
        "consistency_adjustment": 0.02,
        "clv": -0.0074,
        "n_clv_with_data": 9,
        "n_clv_attempted": 9,
        "sharpe": 0.8537,
        "roi_lifetime": 0.3891,
        "roi_180d": 0.3891,
        "roi_90d": 0.3891,
        "roi_30d": 0.3891,
        "max_drawdown_fraction": 0.03,
        "n_resolved": 9,
        "n_distinct_markets": 9,
        "capital_concentration_hhi": 0.1979,
        "win_rate_adj": 0.4526,
        "avg_trades_per_day_30d": 2.1
      },
      "radar": {
        "account_age_days": 9.3,
        "portfolio_value": 463196.0,
        "capital_efficiency": 0.1768,
        "best_leaderboard_rank": 22,
        "profile_views": null,
        "reasons": [
          "passes: efficient/small portfolio, low view count, not top-ranked publicly"
        ]
      },
      "open_positions_count": 15,
      "entry_recommendations": [
        {
          "market_title": "Spain vs. Argentina: Team to Advance",
          "outcome": "Spain",
          "their_entry_price": 0.5905,
          "current_price": 0.5912,
          "fair_value_estimate": 0.59125,
          "suggested_entry_range": [
            0.581,
            0.601
          ],
          "flagged_chasing": false,
          "note": "Price is close to their entry (0.59 -> 0.59); replicating their entry is still reasonably representative.",
          "conviction": 0.1522,
          "pick_score": 0.1522,
          "recommended": true,
          "their_position_value": 431575.9999
        },
        {
          "market_title": "Will Spain vs. Argentina end in a draw?",
          "outcome": "Yes",
          "their_entry_price": 0.3175,
          "current_price": 0.3162,
          "fair_value_estimate": 0.31625,
          "suggested_entry_range": [
            0.307,
            0.327
          ],
          "flagged_chasing": false,
          "note": "Price is close to their entry (0.32 -> 0.32); replicating their entry is still reasonably representative.",
          "conviction": 0.0111,
          "pick_score": 0.0111,
          "recommended": true,
          "their_position_value": 31619.9999
        }
      ]
    },
    {
      "wallet": "0x9b89ef1f344d3e17b37ccdff3bccf62d04f04244",
      "userName": "Woaifacai",
      "display_name": "Woaifacai",
      "profile_url": "https://polymarket.com/@Woaifacai",
      "score": {
        "composite": 0.2974,
        "score_100": 65,
        "kelly_edge": 0.2119,
        "weights_used": {
          "clv": 0.25,
          "sharpe": 0.2,
          "roi_lifetime": 0.15,
          "roi_90d": 0.15,
          "drawdown": 0.1,
          "sample_size": 0.1,
          "win_rate": 0.05
        },
        "consistency_adjustment": 0.02,
        "clv": 0.0333,
        "n_clv_with_data": 40,
        "n_clv_attempted": 40,
        "sharpe": 0.1053,
        "roi_lifetime": 0.0688,
        "roi_180d": 0.0688,
        "roi_90d": 0.0688,
        "roi_30d": 0.069,
        "max_drawdown_fraction": 0.028,
        "n_resolved": 199,
        "n_distinct_markets": 186,
        "capital_concentration_hhi": 0.0199,
        "win_rate_adj": 0.5848,
        "avg_trades_per_day_30d": 14.73
      },
      "radar": {
        "account_age_days": 32.0,
        "portfolio_value": 0,
        "capital_efficiency": 0.0688,
        "best_leaderboard_rank": 45,
        "profile_views": null,
        "reasons": [
          "passes: efficient/small portfolio, low view count, not top-ranked publicly"
        ]
      },
      "open_positions_count": 0,
      "entry_recommendations": []
    }
  ]
}